horhor/__init__.py
horhor/admin_urls.py
horhor/apps.py
horhor/fields.py
horhor/forms.py
horhor/importexport.py
horhor/search_urls.py
horhor/settings.py
horhor/urls.py
horhor/utils.py
horhor/views.py
horhor/wagtail_hooks.py
horhor/widgets.py
horhor/api/mailchimp.py
horhor/bin/__init__.py
horhor/bin/horhor.py
horhor/blocks/__init__.py
horhor/blocks/base_blocks.py
horhor/blocks/content_blocks.py
horhor/blocks/html_blocks.py
horhor/blocks/layout_blocks.py
horhor/blocks/stream_form_blocks.py
horhor/blocks/tests/__init__.py
horhor/blocks/tests/test_blocks.py
horhor/migrations/0001_initial.py
horhor/migrations/0002_auto_20180829_1538.py
horhor/migrations/0003_auto_20180912_1632.py
horhor/migrations/0004_auto_20181119_1507.py
horhor/migrations/0005_auto_20181214_2214.py
horhor/migrations/0006_mailchimpapisettings.py
horhor/migrations/0007_auto_20190114_1515.py
horhor/migrations/0008_auto_20190122_1242.py
horhor/migrations/0009_auto_20190201_1546.py
horhor/migrations/0010_auto_20190320_1231.py
horhor/migrations/0010_generalsettings_email.py
horhor/migrations/0010_remove_generalsettings_robots.py
horhor/migrations/0011_merge_20190322_1309.py
horhor/migrations/0012_merge_20190322_1324.py
horhor/migrations/0013_pagepreview_templates.py
horhor/migrations/0014_classifiers.py
horhor/migrations/0015_coderedsessionformsubmission_coderedsubmissionrevision.py
horhor/migrations/0016_auto_20191025_1620.py
horhor/migrations/0017_generalsettings_external_new_tab.py
horhor/migrations/0018_auto_20200805_1702.py
horhor/migrations/0019_spelling_corrections.py
horhor/migrations/0020_auto_20210527_1030.py
horhor/migrations/0021_auto_20210730_1637.py
horhor/migrations/0022_auto_20210731_1853.py
horhor/migrations/0023_auto_20210908_1702.py
horhor/migrations/0024_analyticssettings.py
horhor/migrations/0025_delete_socialmediasettings.py
horhor/migrations/0026_auto_20220513_1627.py
horhor/migrations/0027_auto_20220603_1142.py
horhor/migrations/0028_auto_20220609_1532.py
horhor-1.2.1.dev2.dist-info/LICENSE
horhor-1.2.1.dev2.dist-info/METADATA
horhor-1.2.1.dev2.dist-info/WHEEL
horhor-1.2.1.dev2.dist-info/entry_points.txt
horhor-1.2.1.dev2.dist-info/top_level.txt
horhor-1.2.1.dev2.dist-info/RECORD
