Metadata-Version: 2.2
Name: horhor
Version: 1.2.1.dev2
Summary: Wagtail-based CMS by CodeRed for building marketing websites.
Home-page: https://github.com/coderedcorp/horhor
Author: CodeRed LLC
Author-email: info@coderedcorp.com
License: BSD License
Classifier: Environment :: Web Environment
Classifier: Framework :: Django
Classifier: Intended Audience :: Developers
Classifier: Operating System :: OS Independent
Classifier: Programming Language :: Python
Classifier: Programming Language :: Python :: 3
Classifier: Programming Language :: Python :: 3.8
Classifier: Programming Language :: Python :: 3.9
Classifier: Programming Language :: Python :: 3.10
Classifier: Programming Language :: Python :: 3.11
Classifier: Programming Language :: Python :: 3 :: Only
Classifier: Framework :: Django
Classifier: Framework :: Django :: 4.1
Classifier: Framework :: Django :: 4.2
Classifier: Framework :: Django :: 5.0
Classifier: Framework :: Wagtail
Classifier: Framework :: Wagtail :: 5
Classifier: Topic :: Internet :: WWW/HTTP
Classifier: Topic :: Internet :: WWW/HTTP :: Dynamic Content
Classifier: Topic :: Internet :: WWW/HTTP :: Site Management
Requires-Python: >=3.8
License-File: LICENSE
Requires-Dist: beautifulsoup4<4.12,>=4.8
Requires-Dist: django-eventtools==1.0.*
Requires-Dist: django-bootstrap5==23.3
Requires-Dist: Django<5.1,>=4.1
Requires-Dist: geocoder==1.38.*
Requires-Dist: icalendar==5.0.*
Requires-Dist: wagtail<6.0,>=5.0
Requires-Dist: wagtail-cache<3,>=2.3
Requires-Dist: wagtail-seo<3,>=2.4
Dynamic: author
Dynamic: author-email
Dynamic: classifier
Dynamic: description
Dynamic: description-content-type
Dynamic: home-page
Dynamic: license
Dynamic: requires-dist
Dynamic: requires-python
Dynamic: summary
